tests/__init__.py
tests/test_client.py
tests/test_models.py
webcrawlerapi/__init__.py
webcrawlerapi/client.py
webcrawlerapi/models.py
webcrawlerapi-2.0.10.dist-info/METADATA
webcrawlerapi-2.0.10.dist-info/WHEEL
webcrawlerapi-2.0.10.dist-info/top_level.txt
webcrawlerapi-2.0.10.dist-info/RECORD
