Metadata-Version: 2.4
Name: webcrawlerapi
Version: 2.0.10
Summary: Python SDK for WebCrawler API
Home-page: https://github.com/webcrawlerapi/webcrawlerapi-python-sdk
Author: Andrew
Classifier: Programming Language :: Python :: 3
Classifier: License :: OSI Approved :: MIT License
Classifier: Operating System :: OS Independent
Requires-Python: >=3.6
Requires-Dist: requests>=2.25.0
Dynamic: author
Dynamic: classifier
Dynamic: description
Dynamic: description-content-type
Dynamic: home-page
Dynamic: requires-dist
Dynamic: requires-python
Dynamic: summary
